hhfundlookthrough/__init__.py
hhfundlookthrough/data.json
hhfundlookthrough/main.py
hhfundlookthrough/multirunmain.py
hhfundlookthrough/alpha/__init__.py
hhfundlookthrough/alpha/multirun.py
hhfundlookthrough/gamma/__init__.py
hhfundlookthrough/gamma/database.py
hhfundlookthrough/gamma/fitresults.py
hhfundlookthrough/gamma/optfunc.py
hhfundlookthrough/gamma/ulib.py
hhfundlookthrough-0.1.6.dist-info/METADATA
hhfundlookthrough-0.1.6.dist-info/WHEEL
hhfundlookthrough-0.1.6.dist-info/top_level.txt
hhfundlookthrough-0.1.6.dist-info/RECORD
