Metadata-Version: 2.2
Name: hhfundlookthrough
Version: 0.1.6
Summary: fundlookthrough
Home-page: https://your.project.url
Author: hh
Author-email: hehuang0717@outlook.com
Classifier: Programming Language :: Python :: 3
Classifier: License :: OSI Approved :: MIT License
Classifier: Operating System :: OS Independent
Requires-Python: >=3.9
Requires-Dist: cvxpy==1.6.0
Requires-Dist: hhfactor
Requires-Dist: scipy==1.13.1
Dynamic: author
Dynamic: author-email
Dynamic: classifier
Dynamic: description
Dynamic: description-content-type
Dynamic: home-page
Dynamic: requires-dist
Dynamic: requires-python
Dynamic: summary
